fake_py_qt.py
fake_py_qt-0.1.1.dist-info/LICENSE
fake_py_qt-0.1.1.dist-info/METADATA
fake_py_qt-0.1.1.dist-info/WHEEL
fake_py_qt-0.1.1.dist-info/entry_points.txt
fake_py_qt-0.1.1.dist-info/top_level.txt
fake_py_qt-0.1.1.dist-info/RECORD
